odoo/addons/account_chart_update_l10n_eu_oss/README.rst
odoo/addons/account_chart_update_l10n_eu_oss/__init__.py
odoo/addons/account_chart_update_l10n_eu_oss/__manifest__.py
odoo/addons/account_chart_update_l10n_eu_oss/i18n/account_chart_update_l10n_eu_oss.pot
odoo/addons/account_chart_update_l10n_eu_oss/i18n/it.po
odoo/addons/account_chart_update_l10n_eu_oss/readme/CONTRIBUTORS.md
odoo/addons/account_chart_update_l10n_eu_oss/readme/DESCRIPTION.md
odoo/addons/account_chart_update_l10n_eu_oss/static/description/icon.png
odoo/addons/account_chart_update_l10n_eu_oss/static/description/index.html
odoo/addons/account_chart_update_l10n_eu_oss/wizard/__init__.py
odoo/addons/account_chart_update_l10n_eu_oss/wizard/wizard_chart_update.py
odoo_addon_account_chart_update_l10n_eu_oss-17.0.1.0.0.4.dist-info/METADATA
odoo_addon_account_chart_update_l10n_eu_oss-17.0.1.0.0.4.dist-info/WHEEL
odoo_addon_account_chart_update_l10n_eu_oss-17.0.1.0.0.4.dist-info/top_level.txt
odoo_addon_account_chart_update_l10n_eu_oss-17.0.1.0.0.4.dist-info/RECORD
